quicklime/__init__.py
quicklime/fetch.py
quicklime/qbottle.py
quicklime/qlook.py
quicklime/static/quicklime/concrete.js
quicklime/static/quicklime/jquery-1.11.1.js
quicklime/static/quicklime/jquery-1.11.1.min.js
quicklime/static/quicklime/jquery.splitter.js
quicklime/static/quicklime/jquery.svg.js
quicklime/static/quicklime/jquery.svgdom.js
quicklime/static/quicklime/quicklime.brat.js
quicklime/static/quicklime/quicklime.css
quicklime/static/quicklime/quicklime.js
quicklime/static/quicklime/quicklime.parse.js
quicklime/static/quicklime/thrift.js
quicklime/static/quicklime/underscore-1.7.0.min.js
quicklime/static/quicklime/bootstrap-3.2.0/css/bootstrap-theme.css
quicklime/static/quicklime/bootstrap-3.2.0/css/bootstrap-theme.css.map
quicklime/static/quicklime/bootstrap-3.2.0/css/bootstrap-theme.min.css
quicklime/static/quicklime/bootstrap-3.2.0/css/bootstrap.css
quicklime/static/quicklime/bootstrap-3.2.0/css/bootstrap.css.map
quicklime/static/quicklime/bootstrap-3.2.0/css/bootstrap.min.css
quicklime/static/quicklime/bootstrap-3.2.0/fonts/glyphicons-halflings-regular.eot
quicklime/static/quicklime/bootstrap-3.2.0/fonts/glyphicons-halflings-regular.svg
quicklime/static/quicklime/bootstrap-3.2.0/fonts/glyphicons-halflings-regular.ttf
quicklime/static/quicklime/bootstrap-3.2.0/fonts/glyphicons-halflings-regular.woff
quicklime/static/quicklime/bootstrap-3.2.0/js/bootstrap.js
quicklime/static/quicklime/bootstrap-3.2.0/js/bootstrap.min.js
quicklime/static/quicklime/brat/client/lib/head.load.min.js
quicklime/static/quicklime/brat/client/lib/jquery-1.7.1.min.js
quicklime/static/quicklime/brat/client/lib/jquery-ui-1.8.16.custom.min.js
quicklime/static/quicklime/brat/client/lib/jquery-ui.combobox.js
quicklime/static/quicklime/brat/client/lib/jquery-ui.min.js
quicklime/static/quicklime/brat/client/lib/jquery.ba-bbq.min.js
quicklime/static/quicklime/brat/client/lib/jquery.json.min.js
quicklime/static/quicklime/brat/client/lib/jquery.min.js
quicklime-0.1.2.dist-info/DESCRIPTION.rst
quicklime-0.1.2.dist-info/METADATA
quicklime-0.1.2.dist-info/RECORD
quicklime-0.1.2.dist-info/WHEEL
quicklime-0.1.2.dist-info/metadata.json
quicklime-0.1.2.dist-info/top_level.txt
