Metadata-Version: 2.0
Name: quicklime
Version: 0.1.2
Summary: UNKNOWN
Home-page: https://github.com/hltcoe/quicklime
Author: Craig Harman
Author-email: craig@craigharman.net
License: BSD
Platform: UNKNOWN
Requires-Dist: bottle
Requires-Dist: concrete (>=4.12.5)
Requires-Dist: humanfriendly
